asana_exporter/__init__.py
asana_exporter/client.py
asana_exporter/utils.py
asana_exporter-1.0.0.post1.dist-info/METADATA
asana_exporter-1.0.0.post1.dist-info/WHEEL
asana_exporter-1.0.0.post1.dist-info/entry_points.txt
asana_exporter-1.0.0.post1.dist-info/top_level.txt
asana_exporter-1.0.0.post1.dist-info/RECORD
