Metadata-Version: 2.1
Name: asana-exporter
Version: 1.0.0.post1
Summary: Python tool to extract data from Asana.
Requires-Python: >=3.8
Requires-Dist: asana
Requires-Dist: jira
Requires-Dist: simplejson
Requires-Dist: importlib-metadata ; python_version >= "3.8"
